aiounu/__init__.py
aiounu-0.1.3.dist-info/LICENSE
aiounu-0.1.3.dist-info/WHEEL
aiounu-0.1.3.dist-info/METADATA
aiounu-0.1.3.dist-info/RECORD
