Metadata-Version: 2.1
Name: aiounu
Version: 0.1.3
Summary: Asyncio module for unu in Python3 using aiohttp.
Home-page: https://github.com/tensortom/aiounu
License: MIT
Keywords: url-shortener,link-shortener,url,shorten,shortener,links,unu,aiohttp,async,asyncio
Author: TensorTom
Author-email: 14287229+TensorTom@users.noreply.github.com
Requires-Python: >=3.7,<4
Classifier: Development Status :: 4 - Beta
Classifier: Environment :: Console
Classifier: Framework :: AsyncIO
Classifier: License :: OSI Approved :: MIT License
Classifier: Operating System :: OS Independent
Classifier: Programming Language :: Python :: 3
Classifier: Programming Language :: Python :: 3.7
Classifier: Programming Language :: Python :: 3.8
Classifier: Programming Language :: Python :: 3.9
Classifier: Topic :: Internet :: WWW/HTTP
Classifier: Topic :: Internet :: WWW/HTTP :: Site Management
Classifier: Topic :: Software Development :: Libraries :: Python Modules
Requires-Dist: aiohttp (>=3.7.3,<4)
Requires-Dist: mo-dots (>=4.2.20340)
Requires-Dist: pytest (>=6.1.1)
Requires-Dist: pytest-aiohttp (>=0.3.0)
Requires-Dist: pytest-asyncio (>=0.14.0)
Project-URL: Repository, https://github.com/tensortom/aiounu
